{
  "name": "Gregory Gardner",
  "age": 18,
  "address": {
    "street": "Fihib Court",
    "city": "Getfatseb",
    "state": "GA",
    "zip": "42976"
  },
  "contact": {
    "phone": "(966) 318-4347",
    "servicePhone": "800257148"
  },
  "birthday": "1978-09-13T22:36:13.840Z",
  "ip": "254.250.199.228",
  "foo": "bar",
  "profile": {
    "about": "Merabsi jucinapur nopke ojagusani ufo gewor wog ruhor dakeoz ato alirowmuh poba ta moj epe. Iro uv osbiz gucov pel uto lu lodjajtag odjon gil git ibusibtut ev navhuhwo ep dazjor patohoj muvnita. Va ku top umjo la heizame asrivvac haz luwabaw mi tun ro. Vawtijda govwivpu fira jived zu uhujug keve tapsufmod megfu kedgagaj wi ecifi rejika gacaj fepnalzi. Ruf orfek wighun ziovad ve mozjo zetujfin kunowu koku nejit wiih ob toseaj web. Fos igpo sehon nepcot jov gukgusu zalbewes rabajojid gu vi vanuzi wetub. Lol za sab ibagicci par he ke ki onibe ohuwehe og we ucutuf limkobloh ju hiakoviw.",
    "bio": "Dimin jilpoj mek sukizavib wup hucugi wajisi gorbe kem co vueg rituvtab duvvirge kudvok ji hoefza zulzu va. Duftof iwjubwal simke acnazce miageci sa wiwado ejo jokakode isedide zeda alaramic maju. Miava ej su tut uvduhu gubto dubu ibe uhsohof sokegapi ziwtofik nug num tipopido amki."
  },
  "apiKey": "511bc391d8a810d3102533426db3063a62f68b6803fbe0644693ac8e0710b2c1",
  "currency": {
    "code": "EGP",
    "name": "Egypt Pound"
  }
}