{
  "name": "Virgie Burns",
  "age": 56,
  "address": {
    "street": "Vehra Point",
    "city": "Usiowfug",
    "state": "NM",
    "zip": "35700"
  },
  "contact": {
    "phone": "(656) 719-6186",
    "servicePhone": "800344126"
  },
  "birthday": "1992-02-13T07:28:41.703Z",
  "ip": "89.239.236.156",
  "foo": "bar",
  "profile": {
    "about": "Idotu gog vej kibsuil vegi vas luvuma pozisjaf kuhusaf law koromi otiikucu bebe lu. Hok pu kebkifro acvudu arwif bunhiciv bab zegju zaut edasizos coriwa tor rujan wuhjon karci zegijepe olopohof. Am ol ohoam sa foovi so efodatvik pi le ro kiubo wi otino mikud zi. Cij ihwom pilvapiz epebo hento naek ip kiwna fiwa warzisub leshiw tilmorve wufhud juriip jeti. Modu uziwi gujud fanat demadkut iviruh wazika voz kas abafitok fukikkad vu vowme soakwow. Gub ji ta hoznofoc kuj ek hob bajlo busuha titijti jurpedro godurogi ca uswaca. Hacpi ur ciud div otfe cibedul lu ejavawof to cauza hula nid.",
    "bio": "Nus de roze fejoc telpoag rutapvu gub ijpob ku zidefu tib idanazu ropec. Jawkevid makap wuwuoce anu desut woj hugfor tazi lo lehtu zavot wikaomu. Va unidupfe ticozi dure hu komdiszul roc hohej wekbo zogrod zafatpow raufuguj laiwa weuhubo netba ko ac asciin. Mo wi ah cad gulep vun dinjevu pi lo fejzafo ermelet vokgavsa ogwohoja is milezi. Hupju fumsol vibnu osahuddoj sa nivpeg udemihe ma ganhamu tapi rupmi de ur vi puci haam. Vaz odane badupac arkesil zopbemike wi hoj ukju ifuuhapa zucahwa reib elevokhu sinlizze aj zu. Huzpa huviwmuk fujgo natnovru bicopa saveposa vawdel niznuses wu ivmuudo zusufbiw vut vam atdit sukuow muwvoeba ositezja nenvocuf."
  },
  "apiKey": "53bd4735867f9f3c48324ea84c6ba17f1a7e43351eaede04e74ce91e650459e6",
  "currency": {
    "code": "KWD",
    "name": "Kuwait Dinar"
  }
}